{
    "model": {
        "canvasBounds": {
            "x": 0,
            "y": 0,
            "width": 2333.75,
            "height": 1168.75
        },
        "scroll": {
            "x": -63,
            "y": -321.39234065345477
        },
        "zoom": 1.4595059412132583,
        "position": {
            "x": 0,
            "y": 0
        },
        "size": {
            "width": -1,
            "height": -1
        },
        "features": {},
        "type": "graph",
        "id": "root",
        "children": [
            {
                "position": {
                    "x": 12,
                    "y": 81.83333333333333
                },
                "size": {
                    "width": 85,
                    "height": 42
                },
                "strokeWidth": 0,
                "selected": false,
                "hoverFeedback": false,
                "opacity": 1,
                "text": "User",
                "color": "var(--color-highlighted)",
                "labels": [
                    {
                        "labelTypeId": "oy2x4o",
                        "labelTypeValueId": "lor4vn"
                    }
                ],
                "ports": [
                    {
                        "position": {
                            "x": 81.5,
                            "y": 1.166666666666666
                        },
                        "size": {
                            "width": 7,
                            "height": 7
                        },
                        "strokeWidth": 0,
                        "selected": false,
                        "hoverFeedback": false,
                        "opacity": 1,
                        "features": {},
                        "behavior": null,
                        "id": "m3ysbfg",
                        "type": "port:dfd-input",
                        "children": []
                    },
                    {
                        "position": {
                            "x": 81.5,
                            "y": 25.666666666666664
                        },
                        "size": {
                            "width": 7,
                            "height": 7
                        },
                        "strokeWidth": 0,
                        "selected": false,
                        "hoverFeedback": false,
                        "opacity": 1,
                        "behavior": "set ClassificationLevel.User",
                        "features": {},
                        "id": "k13qqx",
                        "type": "port:dfd-output",
                        "children": []
                    },
                    {
                        "position": {
                            "x": 81.5,
                            "y": 17.5
                        },
                        "size": {
                            "width": 7,
                            "height": 7
                        },
                        "strokeWidth": 0,
                        "selected": false,
                        "hoverFeedback": false,
                        "opacity": 1,
                        "behavior": "set ClassificationLevel.User",
                        "features": {},
                        "id": "evdd8m",
                        "type": "port:dfd-output",
                        "children": []
                    },
                    {
                        "position": {
                            "x": 81.5,
                            "y": 9.333333333333332
                        },
                        "size": {
                            "width": 7,
                            "height": 7
                        },
                        "strokeWidth": 0,
                        "selected": false,
                        "hoverFeedback": false,
                        "opacity": 1,
                        "behavior": "set ClassificationLevel.User",
                        "features": {},
                        "id": "60sgge",
                        "type": "port:dfd-output",
                        "children": []
                    },
                    {
                        "position": {
                            "x": 81.5,
                            "y": 33.83333333333333
                        },
                        "size": {
                            "width": 7,
                            "height": 7
                        },
                        "strokeWidth": 0,
                        "selected": false,
                        "hoverFeedback": false,
                        "opacity": 1,
                        "behavior": "set ClassificationLevel.UserReceiver\nset ClassificationLevel.User",
                        "features": {},
                        "id": "3t1gqc",
                        "type": "port:dfd-output",
                        "children": []
                    }
                ],
                "hideLabels": false,
                "minimumWidth": 50,
                "annotations": [
                    {
                        "message": "Incoming: ClassificationLevel.User",
                        "icon": "tag",
                        "color": "#FFFFFF",
                        "tfg": 714200711
                    },
                    {
                        "message": "Propagated: ClassificationLevel.User, ClassificationLevel.User, ClassificationLevel.User",
                        "icon": "tag",
                        "color": "#FFFFFF",
                        "tfg": 44635481
                    },
                    {
                        "message": "Propagated: ClassificationLevel.UserReceiver, ClassificationLevel.User",
                        "icon": "tag",
                        "color": "#FFFFFF",
                        "tfg": 686954739
                    },
                    {
                        "message": "Propagated: ClassificationLevel.User, ClassificationLevel.User, ClassificationLevel.User",
                        "icon": "tag",
                        "color": "#FFFFFF",
                        "tfg": 42816138
                    }
                ],
                "features": {},
                "id": "l0qnpt",
                "type": "node:input-output",
                "sourceId": null,
                "targetId": null,
                "children": []
            },
            {
                "position": {
                    "x": 1348,
                    "y": 84.83333333333333
                },
                "size": {
                    "width": 113,
                    "height": 42
                },
                "strokeWidth": 0,
                "selected": false,
                "hoverFeedback": false,
                "opacity": 1,
                "text": "SMS Gameway",
                "color": "#3A1A6E",
                "labels": [
                    {
                        "labelTypeId": "oy2x4o",
                        "labelTypeValueId": "66ru7d"
                    }
                ],
                "ports": [
                    {
                        "position": {
                            "x": -3.5,
                            "y": 17.5
                        },
                        "size": {
                            "width": 7,
                            "height": 7
                        },
                        "strokeWidth": 0,
                        "selected": false,
                        "hoverFeedback": false,
                        "opacity": 1,
                        "features": {},
                        "behavior": null,
                        "id": "e45gpj",
                        "type": "port:dfd-input",
                        "children": []
                    }
                ],
                "hideLabels": false,
                "minimumWidth": 50,
                "annotations": [
                    {
                        "message": "Incoming: ClassificationLevel.User, ClassificationLevel.UserReceiver",
                        "icon": "tag",
                        "color": "#FFFFFF",
                        "tfg": 44635481
                    },
                    {
                        "message": "Incoming: ClassificationLevel.UserReceiver, ClassificationLevel.User",
                        "icon": "tag",
                        "color": "#FFFFFF",
                        "tfg": 686954739
                    },
                    {
                        "message": "Incoming: ClassificationLevel.User",
                        "icon": "tag",
                        "color": "#FFFFFF",
                        "tfg": 42816138
                    },
                    {
                        "message": "Constraint ContactDirect violated",
                        "icon": "bolt",
                        "color": "#3A1A6E",
                        "tfg": 42816138
                    }
                ],
                "features": {},
                "id": "6oilhg",
                "type": "node:input-output",
                "sourceId": null,
                "targetId": null,
                "children": []
            },
            {
                "position": {
                    "x": 394,
                    "y": 48.83333333333333
                },
                "size": {
                    "width": 115,
                    "height": 42
                },
                "strokeWidth": 0,
                "selected": false,
                "hoverFeedback": false,
                "opacity": 1,
                "text": "Contact Store",
                "color": "var(--color-highlighted)",
                "labels": [
                    {
                        "labelTypeId": "oy2x4o",
                        "labelTypeValueId": "lor4vn"
                    }
                ],
                "ports": [
                    {
                        "position": {
                            "x": 111.5,
                            "y": 17.5
                        },
                        "size": {
                            "width": 7,
                            "height": 7
                        },
                        "strokeWidth": 0,
                        "selected": false,
                        "hoverFeedback": false,
                        "opacity": 1,
                        "behavior": "forward add_contact\nforward delete_contact",
                        "features": {},
                        "id": "6b4mqo",
                        "type": "port:dfd-output",
                        "children": []
                    },
                    {
                        "position": {
                            "x": -3.5,
                            "y": 9.333333333333334
                        },
                        "size": {
                            "width": 7,
                            "height": 7
                        },
                        "strokeWidth": 0,
                        "selected": false,
                        "hoverFeedback": false,
                        "opacity": 1,
                        "features": {},
                        "behavior": null,
                        "id": "7qmsx3",
                        "type": "port:dfd-input",
                        "children": []
                    },
                    {
                        "position": {
                            "x": -3.5,
                            "y": 25.66666666666667
                        },
                        "size": {
                            "width": 7,
                            "height": 7
                        },
                        "strokeWidth": 0,
                        "selected": false,
                        "hoverFeedback": false,
                        "opacity": 1,
                        "features": {},
                        "behavior": null,
                        "id": "2pzfek",
                        "type": "port:dfd-input",
                        "children": []
                    }
                ],
                "hideLabels": false,
                "minimumWidth": 50,
                "annotations": [
                    {
                        "message": "Propagated: ClassificationLevel.User",
                        "icon": "tag",
                        "color": "#FFFFFF",
                        "tfg": 714200711
                    },
                    {
                        "message": "Incoming: ClassificationLevel.User, ClassificationLevel.User",
                        "icon": "tag",
                        "color": "#FFFFFF",
                        "tfg": 714200711
                    },
                    {
                        "message": "Propagated: ClassificationLevel.User",
                        "icon": "tag",
                        "color": "#FFFFFF",
                        "tfg": 44635481
                    },
                    {
                        "message": "Incoming: ClassificationLevel.User, ClassificationLevel.User",
                        "icon": "tag",
                        "color": "#FFFFFF",
                        "tfg": 44635481
                    },
                    {
                        "message": "Propagated: ClassificationLevel.User",
                        "icon": "tag",
                        "color": "#FFFFFF",
                        "tfg": 42816138
                    },
                    {
                        "message": "Incoming: ClassificationLevel.User, ClassificationLevel.User",
                        "icon": "tag",
                        "color": "#FFFFFF",
                        "tfg": 42816138
                    }
                ],
                "features": {},
                "id": "mlxxt",
                "type": "node:storage",
                "sourceId": null,
                "targetId": null,
                "children": []
            },
            {
                "position": {
                    "x": 960,
                    "y": 73.66666666666667
                },
                "size": {
                    "width": 118,
                    "height": 46
                },
                "strokeWidth": 0,
                "selected": false,
                "hoverFeedback": false,
                "opacity": 1,
                "text": "Extract Number",
                "color": "var(--color-primary)",
                "labels": [
                    {
                        "labelTypeId": "oy2x4o",
                        "labelTypeValueId": "lor4vn"
                    }
                ],
                "ports": [
                    {
                        "position": {
                            "x": -3.5,
                            "y": 20.5
                        },
                        "size": {
                            "width": 7,
                            "height": 7
                        },
                        "strokeWidth": 0,
                        "selected": false,
                        "hoverFeedback": false,
                        "opacity": 1,
                        "features": {},
                        "behavior": null,
                        "id": "moo80h",
                        "type": "port:dfd-input",
                        "children": []
                    },
                    {
                        "position": {
                            "x": 114.5,
                            "y": 20.5
                        },
                        "size": {
                            "width": 7,
                            "height": 7
                        },
                        "strokeWidth": 0,
                        "selected": false,
                        "hoverFeedback": false,
                        "opacity": 1,
                        "behavior": "forward contact\nset ClassificationLevel.UserReceiver",
                        "features": {},
                        "id": "ck34xw",
                        "type": "port:dfd-output",
                        "children": []
                    }
                ],
                "hideLabels": false,
                "minimumWidth": 50,
                "annotations": [
                    {
                        "message": "Propagated: ClassificationLevel.User, ClassificationLevel.UserReceiver",
                        "icon": "tag",
                        "color": "#FFFFFF",
                        "tfg": 44635481
                    },
                    {
                        "message": "Incoming: ClassificationLevel.User",
                        "icon": "tag",
                        "color": "#FFFFFF",
                        "tfg": 44635481
                    }
                ],
                "features": {},
                "id": "1irllr",
                "type": "node:function",
                "sourceId": null,
                "targetId": null,
                "children": []
            },
            {
                "position": {
                    "x": 1162,
                    "y": 82.83333333333333
                },
                "size": {
                    "width": 112,
                    "height": 46
                },
                "strokeWidth": 0,
                "selected": false,
                "hoverFeedback": false,
                "opacity": 1,
                "text": "Send SMS",
                "color": "#3A1A6E",
                "labels": [
                    {
                        "labelTypeId": "oy2x4o",
                        "labelTypeValueId": "66ru7d"
                    }
                ],
                "ports": [
                    {
                        "position": {
                            "x": 108.5,
                            "y": 20.5
                        },
                        "size": {
                            "width": 7,
                            "height": 7
                        },
                        "strokeWidth": 0,
                        "selected": false,
                        "hoverFeedback": false,
                        "opacity": 1,
                        "behavior": "forward contact_direct|message|number\nassign ClassificationLevel.UserReceiver if ClassificationLevel.UserReceiver from contact_direct|message|number\nassign ClassificationLevel.User if ClassificationLevel.User from contact_direct|message|number",
                        "features": {},
                        "id": "6otywj",
                        "type": "port:dfd-output",
                        "children": []
                    },
                    {
                        "position": {
                            "x": -3.5,
                            "y": 20.5
                        },
                        "size": {
                            "width": 7,
                            "height": 7
                        },
                        "strokeWidth": 0,
                        "selected": false,
                        "hoverFeedback": false,
                        "opacity": 1,
                        "features": {},
                        "behavior": null,
                        "id": "bp424",
                        "type": "port:dfd-input",
                        "children": []
                    }
                ],
                "hideLabels": false,
                "minimumWidth": 50,
                "annotations": [
                    {
                        "message": "Propagated: ClassificationLevel.User, ClassificationLevel.UserReceiver",
                        "icon": "tag",
                        "color": "#FFFFFF",
                        "tfg": 44635481
                    },
                    {
                        "message": "Incoming: ClassificationLevel.User, ClassificationLevel.UserReceiver",
                        "icon": "tag",
                        "color": "#FFFFFF",
                        "tfg": 44635481
                    },
                    {
                        "message": "Propagated: ClassificationLevel.UserReceiver, ClassificationLevel.User",
                        "icon": "tag",
                        "color": "#FFFFFF",
                        "tfg": 686954739
                    },
                    {
                        "message": "Incoming: ClassificationLevel.UserReceiver, ClassificationLevel.User",
                        "icon": "tag",
                        "color": "#FFFFFF",
                        "tfg": 686954739
                    },
                    {
                        "message": "Propagated: ClassificationLevel.User",
                        "icon": "tag",
                        "color": "#FFFFFF",
                        "tfg": 42816138
                    },
                    {
                        "message": "Incoming: ClassificationLevel.User",
                        "icon": "tag",
                        "color": "#FFFFFF",
                        "tfg": 42816138
                    },
                    {
                        "message": "Constraint ContactDirect violated",
                        "icon": "bolt",
                        "color": "#3A1A6E",
                        "tfg": 42816138
                    }
                ],
                "features": {},
                "id": "ztul2",
                "type": "node:function",
                "sourceId": null,
                "targetId": null,
                "children": []
            },
            {
                "routingPoints": [
                    {
                        "x": 1281,
                        "y": 105.83333333333333
                    },
                    {
                        "x": 1341,
                        "y": 105.83333333333333
                    }
                ],
                "selected": false,
                "hoverFeedback": false,
                "opacity": 1,
                "text": "sms",
                "features": {},
                "labels": null,
                "ports": null,
                "id": "b1y4ly",
                "type": "edge:arrow",
                "sourceId": "6otywj",
                "targetId": "e45gpj",
                "annotations": null,
                "children": []
            },
            {
                "routingPoints": [
                    {
                        "x": 1085,
                        "y": 96.66666666666667
                    },
                    {
                        "x": 1135,
                        "y": 96.66666666666667
                    },
                    {
                        "x": 1135,
                        "y": 105.83333333333333
                    },
                    {
                        "x": 1155,
                        "y": 105.83333333333333
                    }
                ],
                "selected": false,
                "hoverFeedback": false,
                "opacity": 1,
                "text": "number",
                "features": {},
                "labels": null,
                "ports": null,
                "id": "tlw26g",
                "type": "edge:arrow",
                "sourceId": "ck34xw",
                "targetId": "bp424",
                "annotations": null,
                "children": []
            },
            {
                "routingPoints": [
                    {
                        "x": 104,
                        "y": 119.16666666666666
                    },
                    {
                        "x": 124,
                        "y": 119.16666666666666
                    },
                    {
                        "x": 124,
                        "y": 163.5
                    },
                    {
                        "x": 1135,
                        "y": 163.5
                    },
                    {
                        "x": 1135,
                        "y": 105.83333333333333
                    },
                    {
                        "x": 1155,
                        "y": 105.83333333333333
                    }
                ],
                "selected": false,
                "hoverFeedback": false,
                "opacity": 1,
                "text": "message",
                "features": {},
                "labels": null,
                "ports": null,
                "id": "kgnkg9",
                "type": "edge:arrow",
                "sourceId": "3t1gqc",
                "targetId": "bp424",
                "annotations": null,
                "children": []
            },
            {
                "position": {
                    "x": 770,
                    "y": 51.666666666666664
                },
                "size": {
                    "width": 106,
                    "height": 46
                },
                "strokeWidth": 0,
                "selected": false,
                "hoverFeedback": false,
                "opacity": 1,
                "text": "Select Contact",
                "color": "var(--color-highlighted)",
                "labels": [
                    {
                        "labelTypeId": "oy2x4o",
                        "labelTypeValueId": "lor4vn"
                    }
                ],
                "ports": [
                    {
                        "position": {
                            "x": -3.5,
                            "y": 28
                        },
                        "size": {
                            "width": 7,
                            "height": 7
                        },
                        "strokeWidth": 0,
                        "selected": false,
                        "hoverFeedback": false,
                        "opacity": 1,
                        "features": {},
                        "behavior": null,
                        "id": "q54wb",
                        "type": "port:dfd-input",
                        "children": []
                    },
                    {
                        "position": {
                            "x": -3.5,
                            "y": 10.5
                        },
                        "size": {
                            "width": 7,
                            "height": 7
                        },
                        "strokeWidth": 0,
                        "selected": false,
                        "hoverFeedback": false,
                        "opacity": 1,
                        "features": {},
                        "behavior": null,
                        "id": "m8eevv",
                        "type": "port:dfd-input",
                        "children": []
                    },
                    {
                        "position": {
                            "x": 102.5,
                            "y": 20.5
                        },
                        "size": {
                            "width": 7,
                            "height": 7
                        },
                        "strokeWidth": 0,
                        "selected": false,
                        "hoverFeedback": false,
                        "opacity": 1,
                        "behavior": "forward contacts\nforward criteria",
                        "features": {},
                        "id": "7lceys",
                        "type": "port:dfd-output",
                        "children": []
                    }
                ],
                "hideLabels": false,
                "minimumWidth": 50,
                "annotations": [
                    {
                        "message": "Propagated: ClassificationLevel.User",
                        "icon": "tag",
                        "color": "#FFFFFF",
                        "tfg": 44635481
                    },
                    {
                        "message": "Incoming: ClassificationLevel.User, ClassificationLevel.User",
                        "icon": "tag",
                        "color": "#FFFFFF",
                        "tfg": 44635481
                    },
                    {
                        "message": "Propagated: ClassificationLevel.User",
                        "icon": "tag",
                        "color": "#FFFFFF",
                        "tfg": 42816138
                    },
                    {
                        "message": "Incoming: ClassificationLevel.User, ClassificationLevel.User",
                        "icon": "tag",
                        "color": "#FFFFFF",
                        "tfg": 42816138
                    }
                ],
                "features": {},
                "id": "74lj1",
                "type": "node:function",
                "sourceId": null,
                "targetId": null,
                "children": []
            },
            {
                "routingPoints": [
                    {
                        "x": 104,
                        "y": 111
                    },
                    {
                        "x": 134,
                        "y": 110.99999999999999
                    },
                    {
                        "x": 134,
                        "y": 145.91666666666669
                    },
                    {
                        "x": 743,
                        "y": 145.91666666666669
                    },
                    {
                        "x": 743,
                        "y": 83.49999999999999
                    },
                    {
                        "x": 763,
                        "y": 83.5
                    }
                ],
                "selected": false,
                "hoverFeedback": false,
                "opacity": 1,
                "text": "criteria",
                "features": {},
                "labels": null,
                "ports": null,
                "id": "yivrib",
                "type": "edge:arrow",
                "sourceId": "k13qqx",
                "targetId": "q54wb",
                "annotations": null,
                "children": []
            },
            {
                "routingPoints": [
                    {
                        "x": 883,
                        "y": 74.66666666666666
                    },
                    {
                        "x": 903,
                        "y": 74.66666666666667
                    },
                    {
                        "x": 903,
                        "y": 96.66666666666667
                    },
                    {
                        "x": 953,
                        "y": 96.66666666666667
                    }
                ],
                "selected": false,
                "hoverFeedback": false,
                "opacity": 1,
                "text": "contact",
                "features": {},
                "labels": null,
                "ports": null,
                "id": "qu94ia",
                "type": "edge:arrow",
                "sourceId": "7lceys",
                "targetId": "moo80h",
                "annotations": null,
                "children": []
            },
            {
                "routingPoints": [
                    {
                        "x": 883,
                        "y": 74.66666666666666
                    },
                    {
                        "x": 903,
                        "y": 74.66666666666667
                    },
                    {
                        "x": 903,
                        "y": 52.66666666666667
                    },
                    {
                        "x": 1135,
                        "y": 52.66666666666667
                    },
                    {
                        "x": 1135,
                        "y": 105.83333333333333
                    },
                    {
                        "x": 1155,
                        "y": 105.83333333333333
                    }
                ],
                "selected": false,
                "hoverFeedback": false,
                "opacity": 1,
                "text": "contact_direct",
                "features": {},
                "labels": null,
                "ports": null,
                "id": "inmelk",
                "type": "edge:arrow",
                "sourceId": "7lceys",
                "targetId": "bp424",
                "annotations": null,
                "children": []
            },
            {
                "position": {
                    "x": 593,
                    "y": 25.750000000000004
                },
                "size": {
                    "width": 93,
                    "height": 46
                },
                "strokeWidth": 0,
                "selected": false,
                "hoverFeedback": false,
                "opacity": 1,
                "text": "List Contacts",
                "color": "var(--color-highlighted)",
                "labels": [
                    {
                        "labelTypeId": "oy2x4o",
                        "labelTypeValueId": "lor4vn"
                    }
                ],
                "ports": [
                    {
                        "position": {
                            "x": -3.5,
                            "y": 28
                        },
                        "size": {
                            "width": 7,
                            "height": 7
                        },
                        "strokeWidth": 0,
                        "selected": false,
                        "hoverFeedback": false,
                        "opacity": 1,
                        "features": {},
                        "behavior": null,
                        "id": "al4e8s",
                        "type": "port:dfd-input",
                        "children": []
                    },
                    {
                        "position": {
                            "x": 89.5,
                            "y": 20.5
                        },
                        "size": {
                            "width": 7,
                            "height": 7
                        },
                        "strokeWidth": 0,
                        "selected": false,
                        "hoverFeedback": false,
                        "opacity": 1,
                        "behavior": "forward contacts",
                        "features": {},
                        "id": "akdvsn",
                        "type": "port:dfd-output",
                        "children": []
                    },
                    {
                        "position": {
                            "x": -3.5,
                            "y": 10.5
                        },
                        "size": {
                            "width": 7,
                            "height": 7
                        },
                        "strokeWidth": 0,
                        "selected": false,
                        "hoverFeedback": false,
                        "opacity": 1,
                        "behavior": "forward contacts",
                        "features": {},
                        "id": "p3p815",
                        "type": "port:dfd-output",
                        "children": []
                    }
                ],
                "hideLabels": false,
                "minimumWidth": 50,
                "annotations": [
                    {
                        "message": "Propagated: ClassificationLevel.User",
                        "icon": "tag",
                        "color": "#FFFFFF",
                        "tfg": 714200711
                    },
                    {
                        "message": "Incoming: ClassificationLevel.User",
                        "icon": "tag",
                        "color": "#FFFFFF",
                        "tfg": 714200711
                    },
                    {
                        "message": "Propagated: ClassificationLevel.User",
                        "icon": "tag",
                        "color": "#FFFFFF",
                        "tfg": 44635481
                    },
                    {
                        "message": "Incoming: ClassificationLevel.User",
                        "icon": "tag",
                        "color": "#FFFFFF",
                        "tfg": 44635481
                    },
                    {
                        "message": "Propagated: ClassificationLevel.User",
                        "icon": "tag",
                        "color": "#FFFFFF",
                        "tfg": 42816138
                    },
                    {
                        "message": "Incoming: ClassificationLevel.User",
                        "icon": "tag",
                        "color": "#FFFFFF",
                        "tfg": 42816138
                    }
                ],
                "features": {},
                "id": "l6zcy5",
                "type": "node:function",
                "sourceId": null,
                "targetId": null,
                "children": []
            },
            {
                "routingPoints": [
                    {
                        "x": 516,
                        "y": 69.83333333333333
                    },
                    {
                        "x": 566,
                        "y": 69.83333333333333
                    },
                    {
                        "x": 566,
                        "y": 57.58333333333333
                    },
                    {
                        "x": 586,
                        "y": 57.58333333333333
                    }
                ],
                "selected": false,
                "hoverFeedback": false,
                "opacity": 1,
                "text": "contacts",
                "features": {},
                "labels": null,
                "ports": null,
                "id": "6z7bt",
                "type": "edge:arrow",
                "sourceId": "6b4mqo",
                "targetId": "al4e8s",
                "annotations": null,
                "children": []
            },
            {
                "routingPoints": [
                    {
                        "x": 693,
                        "y": 48.75
                    },
                    {
                        "x": 743,
                        "y": 48.75
                    },
                    {
                        "x": 743,
                        "y": 65.83333333333333
                    },
                    {
                        "x": 763,
                        "y": 65.83333333333333
                    }
                ],
                "selected": false,
                "hoverFeedback": false,
                "opacity": 1,
                "text": "contacts",
                "features": {},
                "labels": null,
                "ports": null,
                "id": "w5xf6l",
                "type": "edge:arrow",
                "sourceId": "akdvsn",
                "targetId": "m8eevv",
                "annotations": null,
                "children": []
            },
            {
                "routingPoints": [
                    {
                        "x": 586,
                        "y": 39.91666666666667
                    },
                    {
                        "x": 566,
                        "y": 39.91666666666667
                    },
                    {
                        "x": 566,
                        "y": 12
                    },
                    {
                        "x": 124,
                        "y": 12
                    },
                    {
                        "x": 124,
                        "y": 86.5
                    },
                    {
                        "x": 104,
                        "y": 86.5
                    }
                ],
                "selected": false,
                "hoverFeedback": false,
                "opacity": 1,
                "text": "contacts",
                "features": {},
                "labels": null,
                "ports": null,
                "id": "u3zkc",
                "type": "edge:arrow",
                "sourceId": "p3p815",
                "targetId": "m3ysbfg",
                "annotations": null,
                "children": []
            },
            {
                "position": {
                    "x": 201,
                    "y": 23
                },
                "size": {
                    "width": 109,
                    "height": 46
                },
                "strokeWidth": 0,
                "selected": false,
                "hoverFeedback": false,
                "opacity": 1,
                "text": "Delete Contact",
                "color": "var(--color-highlighted)",
                "labels": [
                    {
                        "labelTypeId": "oy2x4o",
                        "labelTypeValueId": "lor4vn"
                    }
                ],
                "ports": [
                    {
                        "position": {
                            "x": -3.5,
                            "y": 20.5
                        },
                        "size": {
                            "width": 7,
                            "height": 7
                        },
                        "strokeWidth": 0,
                        "selected": false,
                        "hoverFeedback": false,
                        "opacity": 1,
                        "features": {},
                        "behavior": null,
                        "id": "02pjt",
                        "type": "port:dfd-input",
                        "children": []
                    },
                    {
                        "position": {
                            "x": 105.5,
                            "y": 20.5
                        },
                        "size": {
                            "width": 7,
                            "height": 7
                        },
                        "strokeWidth": 0,
                        "selected": false,
                        "hoverFeedback": false,
                        "opacity": 1,
                        "behavior": "forward contact",
                        "features": {},
                        "id": "o2gb8r",
                        "type": "port:dfd-output",
                        "children": []
                    }
                ],
                "hideLabels": false,
                "minimumWidth": 50,
                "annotations": [
                    {
                        "message": "Propagated: ClassificationLevel.User",
                        "icon": "tag",
                        "color": "#FFFFFF",
                        "tfg": 714200711
                    },
                    {
                        "message": "Incoming: ClassificationLevel.User",
                        "icon": "tag",
                        "color": "#FFFFFF",
                        "tfg": 714200711
                    },
                    {
                        "message": "Propagated: ClassificationLevel.User",
                        "icon": "tag",
                        "color": "#FFFFFF",
                        "tfg": 44635481
                    },
                    {
                        "message": "Incoming: ClassificationLevel.User",
                        "icon": "tag",
                        "color": "#FFFFFF",
                        "tfg": 44635481
                    },
                    {
                        "message": "Propagated: ClassificationLevel.User",
                        "icon": "tag",
                        "color": "#FFFFFF",
                        "tfg": 42816138
                    },
                    {
                        "message": "Incoming: ClassificationLevel.User",
                        "icon": "tag",
                        "color": "#FFFFFF",
                        "tfg": 42816138
                    }
                ],
                "features": {},
                "id": "2f74m7",
                "type": "node:function",
                "sourceId": null,
                "targetId": null,
                "children": []
            },
            {
                "routingPoints": [
                    {
                        "x": 104,
                        "y": 94.66666666666666
                    },
                    {
                        "x": 134,
                        "y": 94.66666666666666
                    },
                    {
                        "x": 134,
                        "y": 46
                    },
                    {
                        "x": 194,
                        "y": 46
                    }
                ],
                "selected": false,
                "hoverFeedback": false,
                "opacity": 1,
                "text": "contact",
                "features": {},
                "labels": null,
                "ports": null,
                "id": "kuw3en",
                "type": "edge:arrow",
                "sourceId": "60sgge",
                "targetId": "02pjt",
                "annotations": null,
                "children": []
            },
            {
                "position": {
                    "x": 209.5,
                    "y": 88.99999999999999
                },
                "size": {
                    "width": 92,
                    "height": 46
                },
                "strokeWidth": 0,
                "selected": false,
                "hoverFeedback": false,
                "opacity": 1,
                "text": "Add Contact",
                "color": "var(--color-highlighted)",
                "labels": [
                    {
                        "labelTypeId": "oy2x4o",
                        "labelTypeValueId": "lor4vn"
                    }
                ],
                "ports": [
                    {
                        "position": {
                            "x": -3.5,
                            "y": 20.5
                        },
                        "size": {
                            "width": 7,
                            "height": 7
                        },
                        "strokeWidth": 0,
                        "selected": false,
                        "hoverFeedback": false,
                        "opacity": 1,
                        "features": {},
                        "behavior": null,
                        "id": "tszws8",
                        "type": "port:dfd-input",
                        "children": []
                    },
                    {
                        "position": {
                            "x": 88.5,
                            "y": 20.5
                        },
                        "size": {
                            "width": 7,
                            "height": 7
                        },
                        "strokeWidth": 0,
                        "selected": false,
                        "hoverFeedback": false,
                        "opacity": 1,
                        "behavior": "forward contact",
                        "features": {},
                        "id": "q52qe",
                        "type": "port:dfd-output",
                        "children": []
                    }
                ],
                "hideLabels": false,
                "minimumWidth": 50,
                "annotations": [
                    {
                        "message": "Propagated: ClassificationLevel.User",
                        "icon": "tag",
                        "color": "#FFFFFF",
                        "tfg": 714200711
                    },
                    {
                        "message": "Incoming: ClassificationLevel.User",
                        "icon": "tag",
                        "color": "#FFFFFF",
                        "tfg": 714200711
                    },
                    {
                        "message": "Propagated: ClassificationLevel.User",
                        "icon": "tag",
                        "color": "#FFFFFF",
                        "tfg": 44635481
                    },
                    {
                        "message": "Incoming: ClassificationLevel.User",
                        "icon": "tag",
                        "color": "#FFFFFF",
                        "tfg": 44635481
                    },
                    {
                        "message": "Propagated: ClassificationLevel.User",
                        "icon": "tag",
                        "color": "#FFFFFF",
                        "tfg": 42816138
                    },
                    {
                        "message": "Incoming: ClassificationLevel.User",
                        "icon": "tag",
                        "color": "#FFFFFF",
                        "tfg": 42816138
                    }
                ],
                "features": {},
                "id": "9ic5ds",
                "type": "node:function",
                "sourceId": null,
                "targetId": null,
                "children": []
            },
            {
                "routingPoints": [
                    {
                        "x": 104,
                        "y": 102.83333333333333
                    },
                    {
                        "x": 144,
                        "y": 102.83333333333333
                    },
                    {
                        "x": 144,
                        "y": 111.99999999999999
                    },
                    {
                        "x": 202.5,
                        "y": 111.99999999999999
                    }
                ],
                "selected": false,
                "hoverFeedback": false,
                "opacity": 1,
                "text": "contact",
                "features": {},
                "labels": null,
                "ports": null,
                "id": "3w6het",
                "type": "edge:arrow",
                "sourceId": "evdd8m",
                "targetId": "tszws8",
                "annotations": null,
                "children": []
            },
            {
                "routingPoints": [
                    {
                        "x": 317,
                        "y": 46
                    },
                    {
                        "x": 367,
                        "y": 46
                    },
                    {
                        "x": 367,
                        "y": 61.666666666666664
                    },
                    {
                        "x": 387,
                        "y": 61.666666666666664
                    }
                ],
                "selected": false,
                "hoverFeedback": false,
                "opacity": 1,
                "text": "delete_contact",
                "features": {},
                "labels": null,
                "ports": null,
                "id": "60r59e",
                "type": "edge:arrow",
                "sourceId": "o2gb8r",
                "targetId": "7qmsx3",
                "annotations": null,
                "children": []
            },
            {
                "routingPoints": [
                    {
                        "x": 308.5,
                        "y": 111.99999999999999
                    },
                    {
                        "x": 367,
                        "y": 111.99999999999999
                    },
                    {
                        "x": 367,
                        "y": 78
                    },
                    {
                        "x": 387,
                        "y": 78
                    }
                ],
                "selected": true,
                "hoverFeedback": false,
                "opacity": 1,
                "text": "add_contact",
                "features": {},
                "labels": null,
                "ports": null,
                "id": "7f23aq",
                "type": "edge:arrow",
                "sourceId": "q52qe",
                "targetId": "2pzfek",
                "annotations": null,
                "children": []
            }
        ]
    },
    "labelTypes": [
        {
            "id": "oy2x4o",
            "name": "ClearanceLevel",
            "values": [
                {
                    "id": "lor4vn",
                    "text": "User"
                },
                {
                    "id": "66ru7d",
                    "text": "UserReceiver"
                }
            ]
        },
        {
            "id": "08pv8q",
            "name": "ClassificationLevel",
            "values": [
                {
                    "id": "4eyzrb",
                    "text": "User"
                },
                {
                    "id": "xd2p5",
                    "text": "UserReceiver"
                }
            ]
        }
    ],
    "constraints": [
        {
            "name": "ContactDirect",
            "constraint": "data !ClassificationLevel.UserReceiver neverFlows vertex ClearanceLevel.UserReceiver"
        }
    ],
    "mode": "edit",
    "version": 1
}